LICENSE
README.md
setup.cfg
setup.py
namebase_marketplace/__init__.py
namebase_marketplace/enums.py
namebase_marketplace/marketplace.py
namebase_marketplace/utils.py
namebase_marketplace.egg-info/PKG-INFO
namebase_marketplace.egg-info/SOURCES.txt
namebase_marketplace.egg-info/dependency_links.txt
namebase_marketplace.egg-info/requires.txt
namebase_marketplace.egg-info/top_level.txt
test/test.py