Metadata-Version: 2.1
Name: namebase-marketplace
Version: 0.2.94
Summary: Python Client to interact with the Namebase Marketplace API
Home-page: https://github.com/pretended/namebase-marketplace
Author: Roberto Pérez Rico (pretended)
Author-email: robertforperez@gmail.com
Classifier: Programming Language :: Python :: 3
Classifier: Programming Language :: Python :: 3.6
Classifier: Programming Language :: Python :: 3.7
Classifier: License :: OSI Approved :: MIT License
Classifier: Operating System :: OS Independent
Classifier: Intended Audience :: Developers
Classifier: Topic :: Software Development :: Libraries :: Python Modules
Classifier: Natural Language :: English
Requires-Python: >=3.1
License-File: LICENSE
